setup.py
django_teamcity/__init__.py
django_teamcity/settings.py
django_teamcity/test.py
django_teamcity/testcase.py
django_teamcity.egg-info/PKG-INFO
django_teamcity.egg-info/SOURCES.txt
django_teamcity.egg-info/dependency_links.txt
django_teamcity.egg-info/requires.txt
django_teamcity.egg-info/top_level.txt
django_teamcity/management/__init__.py
django_teamcity/management/commands/__init__.py
django_teamcity/management/commands/testproject.py