Metadata-Version: 1.0
Name: django-teamcity
Version: 0.1
Summary: send test result to TeamCity and provide Selenium support
Home-page: https://bitbucket.org/raymank26/django-teamcity
Author: Anton Ermak
Author-email: Rayman.k26@gmail.com
License: BSD
Keywords: unittest teamcity test jetbrains django
Platform: any
